<annotation>
	<folder></folder>
	<filename>1_CAR_15-36-44-178_jpg.rf.20b0a81893de25bc64da4919c036b252.jpg</filename>
	<path>1_CAR_15-36-44-178_jpg.rf.20b0a81893de25bc64da4919c036b252.jpg</path>
	<source>
		<database>roboflow.com</database>
	</source>
	<size>
		<width>629</width>
		<height>571</height>
		<depth>3</depth>
	</size>
	<segmented>0</segmented>
	<object>
		<name>seatbelt</name>
		<pose>Unspecified</pose>
		<truncated>0</truncated>
		<difficult>0</difficult>
		<occluded>0</occluded>
		<bndbox>
			<xmin>485</xmin>
			<xmax>568</xmax>
			<ymin>143</ymin>
			<ymax>193</ymax>
		</bndbox>
	</object>
	<object>
		<name>windshield</name>
		<pose>Unspecified</pose>
		<truncated>0</truncated>
		<difficult>0</difficult>
		<occluded>0</occluded>
		<bndbox>
			<xmin>143</xmin>
			<xmax>602</xmax>
			<ymin>124</ymin>
			<ymax>259</ymax>
		</bndbox>
	</object>
</annotation>
